devpi_private_mirrors/__init__.py
devpi_private_mirrors/main.py
devpi_private_mirrors-0.0.3.dist-info/entry_points.txt
devpi_private_mirrors-0.0.3.dist-info/WHEEL
devpi_private_mirrors-0.0.3.dist-info/METADATA
devpi_private_mirrors-0.0.3.dist-info/licenses/LICENSE
devpi_private_mirrors-0.0.3.dist-info/RECORD
