Metadata-Version: 2.1
Name: devpi-private-mirrors
Version: 0.0.3
Summary: devpi plugin prevent mixing packages using both private and public mirrors
License: MIT
Author-email: strayge <strayge@gmail.ru>
Requires-Python: >=3.10
Classifier: Development Status :: 4 - Beta
Classifier: Environment :: Plugins
Classifier: Intended Audience :: Developers
Classifier: Intended Audience :: System Administrators
Classifier: License :: OSI Approved :: MIT License
Classifier: Natural Language :: English
Classifier: Programming Language :: Python :: 3
Classifier: Programming Language :: Python :: 3.10
Classifier: Programming Language :: Python :: 3.11
Classifier: Topic :: Software Development :: Libraries
Classifier: Topic :: Utilities
Requires-Dist: devpi-server
Provides-Extra: dev
Requires-Dist: flake8-pyproject; extra == "dev"
Requires-Dist: flake8-commas; extra == "dev"
Requires-Dist: flake8-isort!=5.0.1,!=5.0.2; extra == "dev"
Requires-Dist: flake8-bugbear; extra == "dev"
Requires-Dist: flake8-simplify; extra == "dev"
Requires-Dist: flake8-print; extra == "dev"
Requires-Dist: flake8-debugger; extra == "dev"
Requires-Dist: flake8-hangover; extra == "dev"
Requires-Dist: isort; extra == "dev"
Requires-Dist: mypy; extra == "dev"
Project-URL: repository, https://github.com/strayge/devpi-private-mirror
